stayup/__init__.py
stayup/__main__.py
stayup/cli.py
stayup/core.py
stayup-0.1.2.dist-info/METADATA
stayup-0.1.2.dist-info/WHEEL
stayup-0.1.2.dist-info/entry_points.txt
stayup-0.1.2.dist-info/licenses/LICENSE
stayup-0.1.2.dist-info/RECORD
